Sand_to_Silicon_1_30/Day02/kmap.v
module kmap(

    input a,
    input b,
    input c,
    input d,
    output f
);
assign f=d|(~b&~c);
endmodule

Sand_to_Silicon_1_30/Day02/kmap_tb.v
module kmap_tb;
reg a;
reg b;
reg c;
reg d;

wire f;

kmap uut(

    .a(a),
    .b(b),
    .c(c),
    .d(d),
    .f(f)
);

initial begin
    $dumpfile("dump.vcd");
    $dumpvars(0, kmap_tb);
     a=0; b=0; c=0; d=0; #10;
a=0; b=0; c=0; d=1; #10;
a=0; b=0; c=1; d=0; #10;
a=0; b=0; c=1; d=1; #10;
a=0; b=1; c=0; d=0; #10;
a=0; b=1; c=0; d=1; #10;
a=0; b=1; c=1; d=0; #10;
a=0; b=1; c=1; d=1; #10;
a=1; b=0; c=0; d=0; #10;
a=1; b=0; c=0; d=1; #10;
a=1; b=0; c=1; d=0; #10;
a=1; b=0; c=1; d=1; #10;
a=1; b=1; c=0; d=0; #10;
a=1; b=1; c=0; d=1; #10;
a=1; b=1; c=1; d=0; #10;
a=1; b=1; c=1; d=1; #10;

      $finish;

end

initial begin
    $monitor("Time=%0t a=%b b=%b  c=%b d=%b f=%b",
    $time, a, b, c, d, f);
end

endmodule

Sand_to_Silicon_1_30/Day02/dump.vcd
$date
	Sat May 23 13:56:57 2026
$end
$version
	Icarus Verilog
$end
$timescale
	1s
$end
$scope module kmap_tb $end
$var wire 1 ! f $end
$var reg 1 " a $end
$var reg 1 # b $end
$var reg 1 $ c $end
$var reg 1 % d $end
$scope module uut $end
$var wire 1 " a $end
$var wire 1 # b $end
$var wire 1 $ c $end
$var wire 1 % d $end
$var wire 1 ! f $end
$upscope $end
$upscope $end
$enddefinitions $end
$comment Show the parameter values. $end
$dumpall
$end
#0
$dumpvars
0%
0$
0#
0"
1!
$end
#10
1%
#20
0!
0%
1$
#30
1!
1%
#40
0!
0%
0$
1#
#50
1!
1%
#60
0!
0%
1$
#70
1!
1%
#80
1!
0%
0$
0#
1"
#90
1%
#100
0!
0%
1$
#110
1!
1%
#120
0!
0%
0$
1#
#130
1!
1%
#140
0!
0%
1$
#150
1!
1%
