Sand_to_Silicon_1_30/Day03/fulladder.v
module fulladder(

    input wire a,
    input wire b,
    input wire c,
    output wire sum,
    output wire carry
);

assign sum = a^b^c;
assign carry = (a&b)|(b&c)|(a&c);

endmodule

Sand_to_Silicon_1_30/Day03/fulladder_tb.v
module fulladder_tb;

reg a;
reg b;
reg c;
wire sum;
wire carry;

fulladder uut(

    .a(a),
    .b(b),
    .c(c),
    .sum(sum),
    .carry(carry)


);

initial begin
$dumpfile("full_dump.vcd");
$dumpvars(0, fulladder_tb);

   a=0; b=0; c=0; #10;
    a=0; b=0; c=1;  #10;
    a=0; b=1; c=0; #10;
    a=0; b=1; c=1; #10;
    a=1; b=0; c=0; #10;
    a=1; b=0; c=1; #10;
    a=1; b=1; c=0; #10;
    a=1; b=1; c=1; #10;
   
   $finish;
end
 initial begin
    $monitor("Time=%0t a=%b b=%b c=%b sum=%b carry=%b",
    $time, a, b, c, sum, carry);
end

endmodule

Sand_to_Silicon_1_30/Day03/full_dump.vcd
$date
	Sun May 24 13:01:10 2026
$end
$version
	Icarus Verilog
$end
$timescale
	1s
$end
$scope module fulladder_tb $end
$var wire 1 ! sum $end
$var wire 1 " carry $end
$var reg 1 # a $end
$var reg 1 $ b $end
$var reg 1 % c $end
$scope module uut $end
$var wire 1 # a $end
$var wire 1 $ b $end
$var wire 1 % c $end
$var wire 1 " carry $end
$var wire 1 ! sum $end
$upscope $end
$upscope $end
$enddefinitions $end
$comment Show the parameter values. $end
$dumpall
$end
#0
$dumpvars
0%
0$
0#
0"
0!
$end
#10
1!
1%
#20
0%
1$
#30
1"
0!
1%
#40
0"
1!
0%
0$
1#
#50
1"
0!
1%
#60
0%
1$
#70
1!
1%
