Sand_to_Silicon_1_30/Day03/kmap_revision.v
module kmap_revision(

    input a,
    input b,
    input c,
    output y
);

assign y = (a&~c)|(a&b)|(b&~c);
endmodule

Sand_to_Silicon_1_30/Day03/kmap_revision_tb.v
module kmap_revision_tb;

    reg a;
    reg b;
    reg c;
    wire y;


    kmap_revision uut(

        .a(a),
        .b(b),
        .c(c),
        .y(y)
    );

    initial begin

    $dumpfile("rev_kmap_dump.vcd");
    $dumpvars(0,  kmap_revision_tb);

    a=0; b=0; c=0; #10;
    a=0; b=0; c=1;  #10;
    a=0; b=1; c=0; #10;
    a=0; b=1; c=1; #10;
    a=1; b=0; c=0; #10;
    a=1; b=0; c=1; #10;
    a=1; b=1; c=0; #10;
    a=1; b=1; c=1; #10;
   
   $finish;
end 

   initial begin
    $monitor("Time=%0t a=%b b=%b  c=%b y=%b",
    $time, a, b, c, y);
end

endmodule

Sand_to_Silicon_1_30/Day03/rev_kmap_dump.vcd
$date
	Sun May 24 10:53:50 2026
$end
$version
	Icarus Verilog
$end
$timescale
	1s
$end
$scope module kmap_revision_tb $end
$var wire 1 ! y $end
$var reg 1 " a $end
$var reg 1 # b $end
$var reg 1 $ c $end
$scope module uut $end
$var wire 1 " a $end
$var wire 1 # b $end
$var wire 1 $ c $end
$var wire 1 ! y $end
$upscope $end
$upscope $end
$enddefinitions $end
$comment Show the parameter values. $end
$dumpall
$end
#0
$dumpvars
0$
0#
0"
0!
$end
#10
1$
#20
1!
0$
1#
#30
0!
1$
#40
1!
0$
0#
1"
#50
0!
1$
#60
1!
0$
1#
#70
1$
