Sand_to_Silicon_1_30/Day03/fulladder.v
module fulladder(

    input wire a,
    input wire b,
    input wire c,
    output wire sum,
    output wire carry
);

assign sum = a^b^c;
assign carry = (a&b)|(b&c)|(a&c);

endmodule

Sand_to_Silicon_1_30/Day03/ripple.v
module ripple(
    input  [3:0] a,
    input  [3:0] b,
    input        cin,
    output [3:0] sum,
    output       cout
);

    wire c1, c2, c3;  // internal carry wires between stages

    // Stage 0: LSB
    fulladder FA0(.a(a[0]), .b(b[0]), .c(cin),  .sum(sum[0]), .carry(c1));

    // Stage 1: fill this in yourself
    fulladder FA1(.a(a[1]), .b(b[1]), .c(c1), .sum(sum[1]), .carry(c2));

    // Stage 2: fill this in yourself
    fulladder FA2(.a(a[2]), .b(b[2]), .c(c2), .sum(sum[2]), .carry(c3));

    // Stage 3: MSB - fill this in yourself
    fulladder FA3(.a(a[3]), .b(b[3]), .c(c3), .sum(sum[3]), .carry(cout));

endmodule

Sand_to_Silicon_1_30/Day03/ripple_tb.v
module ripple_tb;

reg [3:0] a, b;
reg cin;
wire [3:0] sum;
wire cout;


ripple uut(

    .a(a),
    .b(b),
    .cin(cin),
    .sum(sum),
    .cout(cout)
);

initial begin
$dumpfile("ripple_dump.vcd");
$dumpvars(0, ripple_tb);
a=0; b=0; cin=0; #10;
    a=0; b=0; cin=1;  #10;
    a=0; b=1; cin=0; #10;
    a=0; b=1; cin=1; #10;
    a=1; b=0; cin=0; #10;
    a=1; b=0; cin=1; #10;
    a=1; b=1; cin=0; #10;
    a=1; b=1; cin=1; #10;
   
   $finish;
end
 initial begin
    $monitor("Time=%0t a=%b b=%b cin=%b sum=%b cout=%b",
    $time, a, b, cin, sum, cout);
end

endmodule

Sand_to_Silicon_1_30/Day03/ripple_dump.vcd
$date
	Sun May 24 13:46:58 2026
$end
$version
	Icarus Verilog
$end
$timescale
	1s
$end
$scope module ripple_tb $end
$var wire 4 ! sum [3:0] $end
$var wire 1 " cout $end
$var reg 4 # a [3:0] $end
$var reg 4 $ b [3:0] $end
$var reg 1 % cin $end
$scope module uut $end
$var wire 4 & a [3:0] $end
$var wire 4 ' b [3:0] $end
$var wire 1 % cin $end
$var wire 4 ( sum [3:0] $end
$var wire 1 " cout $end
$var wire 1 ) c3 $end
$var wire 1 * c2 $end
$var wire 1 + c1 $end
$scope module FA0 $end
$var wire 1 , a $end
$var wire 1 - b $end
$var wire 1 % c $end
$var wire 1 + carry $end
$var wire 1 . sum $end
$upscope $end
$scope module FA1 $end
$var wire 1 / a $end
$var wire 1 0 b $end
$var wire 1 + c $end
$var wire 1 * carry $end
$var wire 1 1 sum $end
$upscope $end
$scope module FA2 $end
$var wire 1 2 a $end
$var wire 1 3 b $end
$var wire 1 * c $end
$var wire 1 ) carry $end
$var wire 1 4 sum $end
$upscope $end
$scope module FA3 $end
$var wire 1 5 a $end
$var wire 1 6 b $end
$var wire 1 ) c $end
$var wire 1 " carry $end
$var wire 1 7 sum $end
$upscope $end
$upscope $end
$upscope $end
$enddefinitions $end
$comment Show the parameter values. $end
$dumpall
$end
#0
$dumpvars
07
06
05
04
03
02
01
00
0/
0.
0-
0,
0+
0*
0)
b0 (
b0 '
b0 &
0%
b0 $
b0 #
0"
b0 !
$end
#10
b1 !
b1 (
1.
1%
#20
b1 !
b1 (
1.
1-
0%
b1 $
b1 '
#30
11
1+
b10 !
b10 (
0.
1%
#40
01
0+
b1 !
b1 (
1.
0-
1,
0%
b0 $
b0 '
b1 #
b1 &
#50
11
1+
b10 !
b10 (
0.
1%
#60
11
1+
b10 !
b10 (
0.
1-
0%
b1 $
b1 '
#70
b11 !
b11 (
1.
1%
